hookit/__init__.py
hookit/server.py
hookit-0.9.3.dist-info/METADATA
hookit-0.9.3.dist-info/RECORD
hookit-0.9.3.dist-info/WHEEL
hookit-0.9.3.dist-info/entry_points.txt
hookit-0.9.3.dist-info/top_level.txt
