Metadata-Version: 2.1
Name: hookit
Version: 0.9.3
Summary: Bind GitHub WebHooks to actions
Home-page: https://github.com/tiwilliam/hookit
Author: William Tisäter
Author-email: william@defunct.cc
License: MIT License
Keywords: git github webhook webhooks
Platform: UNKNOWN
Requires-Dist: docopt (>=0.6.0)
Requires-Dist: github3.py (>=0.9.0)
Requires-Dist: ipaddress (>=1.0.6)
